{
    "num_of_hunks": 1,
    "0": {
        "file_name": "src/main/java/com/fasterxml/jackson/databind/deser/BuilderBasedDeserializer.java",
        "from_line_no": 583,
        "to_line_no": 603,
        "replaced_with": "                buffer.assignParameter(creatorProp, creatorProp.deserialize(p, ctxt));\n",
        "replaced": "                if (buffer.assignParameter(creatorProp, creatorProp.deserialize(p, ctxt))) {\n                    t = p.nextToken();\n                    Object bean;\n                    try {\n                        bean = creator.build(ctxt, buffer);\n                    } catch (Exception e) {\n                        wrapAndThrow(e, _beanType.getRawClass(), propName, ctxt);\n                        continue;\n                    }\n                    while (t == JsonToken.FIELD_NAME) {\n                        p.nextToken();\n                        tokens.copyCurrentStructure(p);\n                        t = p.nextToken();\n                    }\n                    tokens.writeEndObject();\n                    if (bean.getClass() != _beanType.getRawClass()) {\n                        ctxt.reportMappingException(\"Can not create polymorphic instances with unwrapped values\");\n                        return null;\n                    }\n                    return _unwrappedPropertyHandler.processUnwrapped(p, ctxt, bean, tokens);\n                }\n",
        "patch_type": "replace",
        "next_line_no": 604
    },
    "num_of_hunks_ci": 1
}