{
    "num_of_hunks": 9,
    "0": {
        "file_name": "src/main/java/com/fasterxml/jackson/databind/deser/impl/CreatorCollector.java",
        "replaced_with": "            boolean verify;\n",
        "patch_type": "insert",
        "next_line_no": 283
    },
    "1": {
        "file_name": "src/main/java/com/fasterxml/jackson/databind/deser/impl/CreatorCollector.java",
        "replaced_with": "                verify = true;\n            } else {\n",
        "patch_type": "insert",
        "next_line_no": 290
    },
    "2": {
        "file_name": "src/main/java/com/fasterxml/jackson/databind/deser/impl/CreatorCollector.java",
        "replaced_with": "                verify = !explicit;\n",
        "patch_type": "insert",
        "next_line_no": 291
    },
    "3": {
        "file_name": "src/main/java/com/fasterxml/jackson/databind/deser/impl/CreatorCollector.java",
        "from_line_no": 294,
        "to_line_no": 294,
        "replaced_with": "            if (verify && (oldOne.getClass() == newOne.getClass())) {\n",
        "replaced": "            if (oldOne.getClass() == newOne.getClass()) {\n",
        "patch_type": "replace",
        "next_line_no": 295
    },
    "4": {
        "file_name": "src/main/java/com/fasterxml/jackson/databind/deser/impl/CreatorCollector.java",
        "replaced_with": "                Class<?> oldType = oldOne.getRawParameterType(0);\n                Class<?> newType = newOne.getRawParameterType(0);\n",
        "patch_type": "insert",
        "next_line_no": 296
    },
    "5": {
        "file_name": "src/main/java/com/fasterxml/jackson/databind/deser/impl/CreatorCollector.java",
        "replaced_with": "                if (oldType == newType) {\n",
        "patch_type": "insert",
        "next_line_no": 297
    },
    "6": {
        "file_name": "src/main/java/com/fasterxml/jackson/databind/deser/impl/CreatorCollector.java",
        "replaced_with": "                }\n",
        "patch_type": "insert",
        "next_line_no": 299
    },
    "7": {
        "file_name": "src/main/java/com/fasterxml/jackson/databind/deser/impl/CreatorCollector.java",
        "replaced_with": "                if (newType.isAssignableFrom(oldType)) {\n",
        "patch_type": "insert",
        "next_line_no": 300
    },
    "8": {
        "file_name": "src/main/java/com/fasterxml/jackson/databind/deser/impl/CreatorCollector.java",
        "replaced_with": "                    return;\n                }\n",
        "patch_type": "insert",
        "next_line_no": 301
    }
}