{
    "num_of_hunks": 2,
    "0": {
        "file_name": "src/java/org/apache/commons/cli/HelpFormatter.java",
        "from_line_no": 824,
        "to_line_no": 824,
        "replaced": "            int lastPos = pos;\n",
        "patch_type": "delete",
        "next_line_no": 825
    },
    "1": {
        "file_name": "src/java/org/apache/commons/cli/HelpFormatter.java",
        "from_line_no": 833,
        "to_line_no": 836,
        "replaced_with": "            }\n            \n            if ( (text.length() > width) && (pos == nextLineTabStop - 1) ) {\n                sb.append(text);\n\n                return sb;\n",
        "replaced": "            } else\n            if (pos == lastPos)\n            {\n                throw new RuntimeException(\"Text too long for line - throwing exception to avoid infinite loop [CLI-162]: \" + text);\n",
        "patch_type": "replace",
        "next_line_no": 837
    }
}