{
    "num_of_hunks": 1,
    "0": {
        "file_name": "src/main/java/com/fasterxml/jackson/databind/deser/std/MapDeserializer.java",
        "from_line_no": 303,
        "to_line_no": 303,
        "replaced_with": "        return (_valueDeserializer == null)\n                && (_keyDeserializer == null)\n                && (_valueTypeDeserializer == null)\n",
        "replaced": "        return (_valueTypeDeserializer == null)\n",
        "patch_type": "replace",
        "next_line_no": 304
    }
}